timeback/__init__.py
timeback/auth.py
timeback/client.py
timeback/config.py
timeback/docs/oneroster/rostering/add_agent.md
timeback/docs/oneroster/rostering/create_user.md
timeback/docs/oneroster/rostering/delete_agent.md
timeback/docs/oneroster/rostering/delete_user.md
timeback/docs/oneroster/rostering/get_agent_for.md
timeback/docs/oneroster/rostering/get_agents.md
timeback/docs/oneroster/rostering/get_all_users.md
timeback/docs/oneroster/rostering/get_user.md
timeback/docs/oneroster/rostering/update_user.md
timeback/docs/package_setup.md
timeback/enums/__init__.py
timeback/enums/timeback_academic_session_type.py
timeback/enums/timeback_agent_type.py
timeback/enums/timeback_assessment_type.py
timeback/enums/timeback_case_version.py
timeback/enums/timeback_class_type.py
timeback/enums/timeback_client_app_status.py
timeback/enums/timeback_difficulty.py
timeback/enums/timeback_enrollment_role.py
timeback/enums/timeback_gender.py
timeback/enums/timeback_guid_type.py
timeback/enums/timeback_importance.py
timeback/enums/timeback_org_type.py
timeback/enums/timeback_qti_cardinality_type.py
timeback/enums/timeback_question_type.py
timeback/enums/timeback_resource_sub_type.py
timeback/enums/timeback_resource_type.py
timeback/enums/timeback_role_name.py
timeback/enums/timeback_role_type.py
timeback/enums/timeback_score_status.py
timeback/enums/timeback_status.py
timeback/enums/timeback_time_spent_type.py
timeback/errors/__init__.py
timeback/errors/errors.py
timeback/http/__init__.py
timeback/http/http.py
timeback/logs/README.md
timeback/logs/__init__.py
timeback/logs/logger.py
timeback/models/__init__.py
timeback/models/errors/__init__.py
timeback/models/errors/timeback_bad_request_response.py
timeback/models/errors/timeback_error_common.py
timeback/models/errors/timeback_forbidden_response.py
timeback/models/errors/timeback_internal_server_error_response.py
timeback/models/errors/timeback_not_found_response.py
timeback/models/errors/timeback_too_many_requests_response.py
timeback-0.1.5.dist-info/METADATA
timeback-0.1.5.dist-info/WHEEL
timeback-0.1.5.dist-info/RECORD
