Metadata-Version: 2.3
Name: timeback
Version: 0.1.5
Summary: A Python client for the TimeBack API (OneRoster 1.2 implementation)
Author: Casey Schmid
Author-email: casey.schmid@2hourlearning.com
Requires-Python: >=3.9,<4.0
Classifier: Programming Language :: Python :: 3
Classifier: Programming Language :: Python :: 3.9
Classifier: Programming Language :: Python :: 3.10
Classifier: Programming Language :: Python :: 3.11
Classifier: Programming Language :: Python :: 3.12
Classifier: Programming Language :: Python :: 3.13
Requires-Dist: httpx (>=0.27.2,<0.28.0)
Requires-Dist: pydantic (>=2.12.3,<3.0.0)
Requires-Dist: python-dotenv (>=1.2.1,<2.0.0)
